apple_compress/__init__.py
apple_compress/__main__.py
apple_compress/_lib.py
apple_compress/compress.py
apple_compress/errors.py
apple_compress/types.py
apple_compress-0.2.2.dist-info/LICENSE
apple_compress-0.2.2.dist-info/METADATA
apple_compress-0.2.2.dist-info/WHEEL
apple_compress-0.2.2.dist-info/entry_points.txt
apple_compress-0.2.2.dist-info/RECORD
