Metadata-Version: 2.1
Name: apple-compress
Version: 0.2.2
Summary: Python bindings for Apple's libcompression.
Author: m1stadev
Author-email: adamhamdi31@gmail.com
Requires-Python: >=3.8,<4.0
Classifier: Programming Language :: Python :: 3
Classifier: Programming Language :: Python :: 3.8
Classifier: Programming Language :: Python :: 3.9
Classifier: Programming Language :: Python :: 3.10
Classifier: Programming Language :: Python :: 3.11
Classifier: Programming Language :: Python :: 3.12
Requires-Dist: click (>=8.1.7,<9.0.0)
Requires-Dist: loguru (>=0.7.2,<0.8.0)
Project-URL: Bug Tracker, https://github.com/m1stadev/apple-compress/issues
Project-URL: Documentation, https://github.com/m1stadev/apple-compress/wiki/API-Usage
